alluxio/__init__.py
alluxio/alluxio_file_system.py
alluxio/worker_ring.py
alluxio_python_library-2.0.1.dist-info/LICENSE
alluxio_python_library-2.0.1.dist-info/METADATA
alluxio_python_library-2.0.1.dist-info/WHEEL
alluxio_python_library-2.0.1.dist-info/top_level.txt
alluxio_python_library-2.0.1.dist-info/RECORD
